destine_auth/__init__.py
destine_auth/de_token.py
destine_auth/dedl_auth.py
destine_auth/desp_auth.py
destine_lab-0.1.dist-info/METADATA
destine_lab-0.1.dist-info/WHEEL
destine_lab-0.1.dist-info/top_level.txt
destine_lab-0.1.dist-info/RECORD
