Metadata-Version: 2.1
Name: destine-lab
Version: 0.1
Requires-Dist: requests
Requires-Dist: lxml
